LICENSE
MANIFEST.in
README.rst
setup.py
Time2Pull.egg-info/PKG-INFO
Time2Pull.egg-info/SOURCES.txt
Time2Pull.egg-info/dependency_links.txt
Time2Pull.egg-info/entry_points.txt
Time2Pull.egg-info/not-zip-safe
Time2Pull.egg-info/top_level.txt
doc/Makefile
doc/conf.py
doc/index.rst
doc/make.bat
doc/_static/Time2Pull.png
doc/_static/Time2PullOverlays.png
share/Time2Pull.desktop
time2pull/__init__.py
time2pull/app.py
time2pull/constants.py
time2pull/icons.py
time2pull/settings.py
time2pull/window.py
time2pull/worker.py
time2pull/forms/__init__.py
time2pull/forms/main_window.ui
time2pull/forms/main_window_ui.py
time2pull/forms/resources.qrc
time2pull/forms/resources_rc.py
time2pull/forms/icons/Database.png
time2pull/forms/icons/DatabaseDirty.png
time2pull/forms/icons/Download-dark.png
time2pull/forms/icons/Download-light.png
time2pull/forms/icons/Download.png
time2pull/forms/icons/DownloadUpload.png
time2pull/forms/icons/Time2Pull.ico
time2pull/forms/icons/Time2Pull.png
time2pull/forms/icons/Time2Pull_banner.png
time2pull/forms/icons/Upload.png
time2pull/forms/icons/add.png
time2pull/forms/icons/exit.png
time2pull/forms/icons/help.png
time2pull/forms/icons/info.png
time2pull/forms/icons/loader.gif
time2pull/forms/icons/remove.png
time2pull/forms/icons/view-refresh.png
time2pull/forms/sounds/sonar.wav