Metadata-Version: 1.1
Name: Time2Pull
Version: 1.0.2.1
Summary: Get notified when your remote git repository got updated!
Home-page: https://github.com/ColinDuquesnoy/Time2Pull
Author: Colin Duquesnoy
Author-email: colin.duquesnoy@gmail.com
License: GPL v3
Keywords: Git; Pull; Time to pull; pull notification
Platform: UNKNOWN
Classifier: Development Status :: 5 - Production/Stable
Classifier: Environment :: X11 Applications :: Qt
Classifier: Environment :: Win32 (MS Windows)
Classifier: Intended Audience :: Developers
Classifier: License :: OSI Approved :: GNU General Public License v3 or later (GPLv3+)
Classifier: Operating System :: Microsoft :: Windows
Classifier: Operating System :: POSIX :: Linux
Classifier: Programming Language :: Python :: 3.2
Classifier: Programming Language :: Python :: 3.3
Classifier: Programming Language :: Python :: 3.4
